sharefly/__init__.py
sharefly/__main__.py
sharefly-0.0.9.dist-info/LICENSE
sharefly-0.0.9.dist-info/METADATA
sharefly-0.0.9.dist-info/WHEEL
sharefly-0.0.9.dist-info/top_level.txt
sharefly-0.0.9.dist-info/RECORD
