Metadata-Version: 2.1
Name: sharefly
Version: 0.0.9
Summary: Flask based web app for sharing files and quiz evaluation
Home-page: https://github.com/NelsonSharma/sharefly
Author: Nelson.S
Author-email: mail.nelsonsharma@gmail.com
Classifier: License :: OSI Approved :: MIT License
License-File: LICENSE
